[
  {
    "name": "Test oracle",
    "trusted": true,
    "url": "https://theoracle.com",
    "description_markdown": "# Markdown describing the oracle provider\n\nSome markdown describing the oracle provider.\n\nTwitter: @FacesPics2\n",
    "oracles": [
      {
        "status": "GOOD",
        "status_reason": "",
        "proofs": [
          {
            "type": "Url",
            "url": "https://acme.io/proof.txt"
          },
          {
            "type": "SignedMessage",
            "message": "some hex"
          }
        ],
        "first_verified": "2022-01-01T00:00:00.000Z",
        "last_verified": "2022-12-31T00:00:00.000Z",
        "type": "PubKey",
        "key": "69464e35bcb8e8a2900ca0f87acaf252d50cf2ab2fc73694845a16b7c8a0dc6f"
      },
      {
        "status": "GOOD",
        "status_reason": "",
        "proofs": [
          {
            "type": "Url",
            "url": "https://twitter.com/user/tweet/etc"
          },
          {
            "type": "SignedMessage",
            "message": "some hex"
          }
        ],
        "first_verified": "2022-01-01T00:00:00.000Z",
        "last_verified": "2022-12-31T00:00:00.000Z",
        "type": "ETHAddress",
        "address": "0x949AF81E51D57831AE52591d17fBcdd1014a5f52"
      }
    ],
    "github_link": "https://github.com/vegaprotocol/well-known/blob/feat/add-process-script/oracle-providers/test-oracle.toml"
  }
]